tesserhocr2df/README.MD
tesserhocr2df/__init__.py
tesserhocr2df/requirements.txt
tesserhocr2df/thirdparty.json
tesserhocr2df-0.10.dist-info/LICENSE.rst
tesserhocr2df-0.10.dist-info/METADATA
tesserhocr2df-0.10.dist-info/WHEEL
tesserhocr2df-0.10.dist-info/top_level.txt
tesserhocr2df-0.10.dist-info/RECORD
